semantic_version/__init__.py
semantic_version/base.py
semantic_version/django_fields.py
semantic_version-2.9.0.dist-info/LICENSE
semantic_version-2.9.0.dist-info/METADATA
semantic_version-2.9.0.dist-info/WHEEL
semantic_version-2.9.0.dist-info/top_level.txt
semantic_version-2.9.0.dist-info/RECORD
