Metadata-Version: 2.1
Name: semantic_version
Version: 2.9.0
Summary: A library implementing the 'SemVer' scheme.
Home-page: https://github.com/rbarrois/python-semanticversion
Author: Raphaël Barrois
Author-email: raphael.barrois+semver@polytechnique.org
License: BSD
Keywords: semantic version,versioning,version
Platform: UNKNOWN
Classifier: Development Status :: 5 - Production/Stable
Classifier: Intended Audience :: Developers
Classifier: License :: OSI Approved :: BSD License
Classifier: Topic :: Software Development :: Libraries :: Python Modules
Classifier: Operating System :: OS Independent
Classifier: Programming Language :: Python
Classifier: Programming Language :: Python :: 2.7
Classifier: Programming Language :: Python :: 3
Classifier: Programming Language :: Python :: 3.4
Classifier: Programming Language :: Python :: 3.5
Classifier: Programming Language :: Python :: 3.6
Classifier: Programming Language :: Python :: 3.7
Classifier: Programming Language :: Python :: 3.8
Classifier: Programming Language :: Python :: 3.9
Classifier: Programming Language :: Python :: 3.10
Classifier: Topic :: Software Development :: Libraries :: Python Modules
Requires-Python: >=2.7
Provides-Extra: dev
Provides-Extra: doc
License-File: LICENSE
